{
    "incomeStatementHistoryQuarterly": {
      "incomeStatementHistory": [
        {
          "maxAge": 1,
          "endDate": "2022-03-31T00:00:00.000Z",
          "totalRevenue": 18756000000,
          "costOfRevenue": 13296000000,
          "grossProfit": 5460000000,
          "researchDevelopment": 865000000,
          "sellingGeneralAdministrative": 992000000,
          "nonRecurring": null,
          "otherOperatingExpenses": null,
          "totalOperatingExpenses": 15153000000,
          "operatingIncome": 3603000000,
          "totalOtherIncomeExpenseNet": 23000000,
          "ebit": 3603000000,
          "interestExpense": -61000000,
          "incomeBeforeTax": 3626000000,
          "incomeTaxExpense": 346000000,
          "minorityInterest": 1321000000,
          "netIncomeFromContinuingOps": 3280000000,
          "discontinuedOperations": null,
          "extraordinaryItems": null,
          "effectOfAccountingCharges": null,
          "otherItems": null,
          "netIncome": 3318000000,
          "netIncomeApplicableToCommonShares": 3318000000
        },
        {
          "maxAge": 1,
          "endDate": "2021-12-31T00:00:00.000Z",
          "totalRevenue": 17719000000,
          "costOfRevenue": 12872000000,
          "grossProfit": 4847000000,
          "researchDevelopment": 740000000,
          "sellingGeneralAdministrative": 1494000000,
          "nonRecurring": null,
          "otherOperatingExpenses": null,
          "totalOperatingExpenses": 15106000000,
          "operatingIncome": 2613000000,
          "totalOtherIncomeExpenseNet": 22000000,
          "ebit": 2613000000,
          "interestExpense": -70000000,
          "incomeBeforeTax": 2635000000,
          "incomeTaxExpense": 292000000,
          "minorityInterest": 1394000000,
          "netIncomeFromContinuingOps": 2343000000,
          "discontinuedOperations": null,
          "extraordinaryItems": null,
          "effectOfAccountingCharges": null,
          "otherItems": null,
          "netIncome": 2321000000,
          "netIncomeApplicableToCommonShares": 2326000000
        },
        {
          "maxAge": 1,
          "endDate": "2021-09-30T00:00:00.000Z",
          "totalRevenue": 13757000000,
          "costOfRevenue": 10097000000,
          "grossProfit": 3660000000,
          "researchDevelopment": 611000000,
          "sellingGeneralAdministrative": 994000000,
          "nonRecurring": null,
          "otherOperatingExpenses": 51000000,
          "totalOperatingExpenses": 11753000000,
          "operatingIncome": 2004000000,
          "totalOtherIncomeExpenseNet": -122000000,
          "ebit": 2004000000,
          "interestExpense": -125000000,
          "incomeBeforeTax": 1882000000,
          "incomeTaxExpense": 223000000,
          "minorityInterest": 1441000000,
          "netIncomeFromContinuingOps": 1659000000,
          "discontinuedOperations": null,
          "extraordinaryItems": null,
          "effectOfAccountingCharges": null,
          "otherItems": null,
          "netIncome": 1618000000,
          "netIncomeApplicableToCommonShares": 1618000000
        },
        {
          "maxAge": 1,
          "endDate": "2021-06-30T00:00:00.000Z",
          "totalRevenue": 11958000000,
          "costOfRevenue": 9074000000,
          "grossProfit": 2884000000,
          "researchDevelopment": 576000000,
          "sellingGeneralAdministrative": 973000000,
          "nonRecurring": null,
          "otherOperatingExpenses": 23000000,
          "totalOperatingExpenses": 10646000000,
          "operatingIncome": 1312000000,
          "totalOtherIncomeExpenseNet": -19000000,
          "ebit": 1312000000,
          "interestExpense": -84000000,
          "incomeBeforeTax": 1293000000,
          "incomeTaxExpense": 115000000,
          "minorityInterest": 1446000000,
          "netIncomeFromContinuingOps": 1178000000,
          "discontinuedOperations": null,
          "extraordinaryItems": null,
          "effectOfAccountingCharges": null,
          "otherItems": null,
          "netIncome": 1142000000,
          "netIncomeApplicableToCommonShares": 1142000000
        }
      ],
      "maxAge": 86400
    }
  }